{
  "project_info": {
    "project_number": "300036803649",
    "project_id": "space-advent",
    "storage_bucket": "space-advent.appspot.com"
  },
  "client": [
    {
      "client_info": {
        "mobilesdk_app_id": "1:300036803649:android:b1f55a1af25f0e8a17cac0",
        "android_client_info": {
          "package_name": "com.example.spaceadventure"
        }
      },
      "oauth_client": [
        {
          "client_id": "300036803649-jh180qralcljq1r5qc7rhh5k27ojuip9.apps.googleusercontent.com",
          "client_type": 3
        }
      ],
      "api_key": [
        {
          "current_key": "AIzaSyCFx0_oYAvAYTNsnxPg_pdqfNLPXDW0Pjw"
        }
      ],
      "services": {
        "appinvite_service": {
          "other_platform_oauth_client": [
            {
              "client_id": "300036803649-jh180qralcljq1r5qc7rhh5k27ojuip9.apps.googleusercontent.com",
              "client_type": 3
            }
          ]
        }
      }
    }
  ],
  "configuration_version": "1"
}